baekjoon/__init__.py
baekjoon/__main__.py
baekjoon/_http.py
baekjoon/boj.py
baekjoon/config.py
baekjoon/constants.py
baekjoon/init.py
baekjoon/judge.py
baekjoon/login.py
baekjoon/solved.py
baekjoon/submit.py
baekjoon/ui.py
baekjoon/util.py
bojtools-0.5.8.dist-info/licenses/LICENSE
bojtools-0.5.8.dist-info/METADATA
bojtools-0.5.8.dist-info/WHEEL
bojtools-0.5.8.dist-info/entry_points.txt
bojtools-0.5.8.dist-info/top_level.txt
bojtools-0.5.8.dist-info/RECORD
