Metadata-Version: 2.4
Name: bojtools
Version: 0.5.8
Home-page: https://github.com/zshchun/bojtools
Author: Seunghwan Chun
Author-email: zshchun@gmail.com
License-File: LICENSE
Requires-Dist: tomli
Requires-Dist: tomli-w
Requires-Dist: aiohttp
Requires-Dist: lxml
Requires-Dist: nodriver
Dynamic: license-file
